asukiaaa_py_i2c_lcd/__init__.py
asukiaaa_py_i2c_lcd/core.py
asukiaaa_py_i2c_lcd-0.1.4.dist-info/DESCRIPTION.rst
asukiaaa_py_i2c_lcd-0.1.4.dist-info/METADATA
asukiaaa_py_i2c_lcd-0.1.4.dist-info/RECORD
asukiaaa_py_i2c_lcd-0.1.4.dist-info/WHEEL
asukiaaa_py_i2c_lcd-0.1.4.dist-info/metadata.json
asukiaaa_py_i2c_lcd-0.1.4.dist-info/top_level.txt
