Metadata-Version: 2.0
Name: asukiaaa-py-i2c-lcd
Version: 0.1.4
Summary: An i2c library to control AQM1602
Home-page: https://github.com/asukiaaa/asukiaaa_py_i2c_lcd
Author: Asuki Kono
Author-email: asukiaaa@gmail.com
License: MIT
Keywords: i2c lcd aqm1602 raspberry
Platform: UNKNOWN
Classifier: Development Status :: 4 - Beta
Classifier: License :: OSI Approved :: MIT License
Classifier: Programming Language :: Python :: 2
Classifier: Programming Language :: Python :: 2.6
Classifier: Programming Language :: Python :: 2.7
Classifier: Programming Language :: Python :: 3
Classifier: Programming Language :: Python :: 3.3
Classifier: Programming Language :: Python :: 3.4
Classifier: Programming Language :: Python :: 3.5
Classifier: Programming Language :: Python :: 3.6
